{
    "tiles": {
        "primary": {
            "startDir": 423,
            "endDir": 430,
            "startTile": 75,
            "endTile": 88
        },
        "secondaries": [
            {
                "startDir": 424,
                "endDir": 428,
                "startTile": 69,
                "endTile": 75
            },
            {
                "startDir": 422,
                "endDir": 428,
                "startTile": 100,
                "endTile": 104
            },
            {
                "startDir": 458,
                "endDir": 464,
                "startTile": 68,
                "endTile": 71
            }
        ]
    }
}
